uisp_crm/__init__.py
uisp_crm/clients/__init__.py
uisp_crm/clients/clients.py
uisp_crm/crm.py
uisp_crm-0.1.1.dist-info/METADATA
uisp_crm-0.1.1.dist-info/WHEEL
uisp_crm-0.1.1.dist-info/RECORD
