Metadata-Version: 2.1
Name: uisp-crm
Version: 0.1.1
Summary: Python library to interact with the Ubiquiti UISP CRM console.
Home-page: https://github.com/thecyberbutler/uisp_crm
License: MIT
Keywords: uisp,ubiquiti,cmr
Author: thecyberbutler
Author-email: michaelbutler75@gmail.com
Requires-Python: >=3.10,<4.0
Classifier: License :: OSI Approved :: MIT License
Classifier: Programming Language :: Python :: 3
Classifier: Programming Language :: Python :: 3.10
Classifier: Programming Language :: Python :: 3.11
Classifier: Programming Language :: Python :: 3.12
Requires-Dist: requests (>=2.31.0,<3.0.0)
Project-URL: Repository, https://github.com/thecyberbutler/uisp_crm
